backtest_pkg/__init__.py
backtest_pkg/backtest_portfolio.py
backtest_pkg/backtest_trading_system.py
backtest_pkg-0.2.1.dist-info/LICENSE
backtest_pkg-0.2.1.dist-info/METADATA
backtest_pkg-0.2.1.dist-info/WHEEL
backtest_pkg-0.2.1.dist-info/top_level.txt
backtest_pkg-0.2.1.dist-info/RECORD
