Metadata-Version: 2.1
Name: backtest-pkg
Version: 0.2.1
Summary: A package for backtesting portfolio strategies and trading signals
Home-page: https://github.com/andyhu4023/backtest_pkg.git
Author: Andy Hu
Author-email: andyhu2014@gmail.com
License: UNKNOWN
Platform: UNKNOWN
Classifier: Programming Language :: Python :: 3
Classifier: License :: OSI Approved :: MIT License
Classifier: Operating System :: OS Independent
Requires-Python: >=3.6
